VoltagePy/VoltagePy.py
VoltagePy/__init__.py
VoltagePy-1.1.1.dist-info/LICENSE
VoltagePy-1.1.1.dist-info/METADATA
VoltagePy-1.1.1.dist-info/WHEEL
VoltagePy-1.1.1.dist-info/entry_points.txt
VoltagePy-1.1.1.dist-info/top_level.txt
VoltagePy-1.1.1.dist-info/RECORD
