Metadata-Version: 2.1
Name: VoltagePy
Version: 1.1.1
Summary: UNKNOWN
Home-page: https://github.com/Heroadn/VoltagePy
Author: Heroadn H.Kaiser
Author-email: benbenjamin554@gmail.com
License: License :: OSI Approved :: MIT License
Platform: UNKNOWN
Classifier: Programming Language :: Python
Requires-Python: >=3.6
Requires-Dist: selenium
Requires-Dist: urllib3
